{
  "sha": null,
  "matrix": {
    "voip_C_02_COMPSPKR_MK.wav": {
      "mos": 3.50149,
      "size": 20125,
      "bitrate": 21.024279386294754,
      "bitrate_target": 16,
      "time": 0.020391225814819336,
      "md5": "735aa21296cc86e7fd504334c3d9ec05",
      "thresh": 2.5,
      "scenario": "voip",
      "filename": "C_02_COMPSPKR_MK.wav"
    },
    "voip_C_02_CHOP_FA.wav": {
      "mos": 3.68391,
      "size": 20195,
      "bitrate": 19.16204595997035,
      "bitrate_target": 16,
      "time": 0.02344059944152832,
      "md5": "606e4f156900b1c9bf259ebe2b384a0b",
      "thresh": 2.5,
      "scenario": "voip",
      "filename": "C_02_CHOP_FA.wav"
    },
    "voip_C_01_COMPSPKR_MK.wav": {
      "mos": 3.50189,
      "size": 20965,
      "bitrate": 22.4594278711162,
      "bitrate_target": 16,
      "time": 0.024666309356689453,
      "md5": "f9a4dead16b42e76c1e235f454a89745",
      "thresh": 2.5,
      "scenario": "voip",
      "filename": "C_01_COMPSPKR_MK.wav"
    },
    "voip_C_01_CHOP_FA.wav": {
      "mos": 3.60373,
      "size": 21028,
      "bitrate": 19.45165490656964,
      "bitrate_target": 16,
      "time": 0.030046701431274414,
      "md5": "72f4abec40871a7565b8a3bfe5dbd1e5",
      "thresh": 2.5,
      "scenario": "voip",
      "filename": "C_01_CHOP_FA.wav"
    },
    "voip_C_04_CHOP_FA.wav": {
      "mos": 3.1505,
      "size": 22724,
      "bitrate": 19.51329887692696,
      "bitrate_target": 16,
      "time": 0.024645090103149414,
      "md5": "75abbbf64bb06d3807b0fd21fa5543f9",
      "thresh": 2.5,
      "scenario": "voip",
      "filename": "C_04_CHOP_FA.wav"
    },
    "voip_C_03_COMPSPKR_MK.wav": {
      "mos": 4.02024,
      "size": 23798,
      "bitrate": 24.985390061409642,
      "bitrate_target": 16,
      "time": 0.02080059051513672,
      "md5": "0b5c3e6468505d7a4cce9995f66eac43",
      "thresh": 2.5,
      "scenario": "voip",
      "filename": "C_03_COMPSPKR_MK.wav"
    },
    "voip_C_03_CHOP_FA.wav": {
      "mos": 2.95797,
      "size": 21785,
      "bitrate": 19.571163774526,
      "bitrate_target": 16,
      "time": 0.030805349349975586,
      "md5": "8fcee1c2052fa99badc323830c730e59",
      "thresh": 2.5,
      "scenario": "voip",
      "filename": "C_03_CHOP_FA.wav"
    },
    "voip_C_04_COMPSPKR_MK.wav": {
      "mos": 3.88095,
      "size": 21055,
      "bitrate": 24.023602576247555,
      "bitrate_target": 16,
      "time": 0.023491621017456055,
      "md5": "920437ad430dd2b2418d3f453532e860",
      "thresh": 2.5,
      "scenario": "voip",
      "filename": "C_04_COMPSPKR_MK.wav"
    },
    "voip_C_05_COMPSPKR_MK.wav": {
      "mos": 3.55528,
      "size": 22965,
      "bitrate": 26.710037766527925,
      "bitrate_target": 16,
      "time": 0.037271976470947266,
      "md5": "824931a324ccaedcf310820a2bc536eb",
      "thresh": 2.5,
      "scenario": "voip",
      "filename": "C_05_COMPSPKR_MK.wav"
    },
    "voip_C_05_CHOP_FA.wav": {
      "mos": 1.63073,
      "size": 23878,
      "bitrate": 19.1024,
      "bitrate_target": 16,
      "time": 0.03875112533569336,
      "md5": "c2bff150c0f9a28ac8690e660400cad3",
      "thresh": 2.5,
      "scenario": "voip",
      "filename": "C_05_CHOP_FA.wav"
    },
    "voip_C_06_CHOP_FA.wav": {
      "mos": 3.52309,
      "size": 21934,
      "bitrate": 19.466201503673986,
      "bitrate_target": 16,
      "time": 0.043230533599853516,
      "md5": "eb379ce0b45f1449653e16210d310119",
      "thresh": 2.5,
      "scenario": "voip",
      "filename": "C_06_CHOP_FA.wav"
    },
    "voip_C_06_COMPSPKR_MK.wav": {
      "mos": 4.02884,
      "size": 21769,
      "bitrate": 23.805686588988433,
      "bitrate_target": 16,
      "time": 0.03669571876525879,
      "md5": "e497d91ce86b6394d871b744b7aa0c95",
      "thresh": 2.5,
      "scenario": "voip",
      "filename": "C_06_COMPSPKR_MK.wav"
    },
    "voip_C_07_CHOP_FA.wav": {
      "mos": 3.67416,
      "size": 21813,
      "bitrate": 19.061319788637203,
      "bitrate_target": 16,
      "time": 0.04548382759094238,
      "md5": "99eaacf522bf39eabb4a20c6f3508dee",
      "thresh": 2.5,
      "scenario": "voip",
      "filename": "C_07_CHOP_FA.wav"
    },
    "voip_C_07_COMPSPKR_MK.wav": {
      "mos": 3.47441,
      "size": 22771,
      "bitrate": 24.394163226958597,
      "bitrate_target": 16,
      "time": 0.03287792205810547,
      "md5": "420aabf34dc857eaebeba2f3840c7c2d",
      "thresh": 2.5,
      "scenario": "voip",
      "filename": "C_07_COMPSPKR_MK.wav"
    },
    "voip_C_08_CHOP_FA.wav": {
      "mos": 3.70578,
      "size": 22823,
      "bitrate": 20.81485321221508,
      "bitrate_target": 16,
      "time": 0.04083728790283203,
      "md5": "e1b624c329a33196a91c17e5bb04d40b",
      "thresh": 2.5,
      "scenario": "voip",
      "filename": "C_08_CHOP_FA.wav"
    },
    "voip_C_08_COMPSPKR_MK.wav": {
      "mos": 3.91504,
      "size": 18609,
      "bitrate": 20.782019962308926,
      "bitrate_target": 16,
      "time": 0.02953052520751953,
      "md5": "602849735fe9f9feacf305842d86c596",
      "thresh": 2.5,
      "scenario": "voip",
      "filename": "C_08_COMPSPKR_MK.wav"
    },
    "voip_C_09_CHOP_FA.wav": {
      "mos": 3.72581,
      "size": 19942,
      "bitrate": 20.290262057962874,
      "bitrate_target": 16,
      "time": 0.031061172485351562,
      "md5": "ddff4b9d0ba277f51a98b63b3db2d53f",
      "thresh": 2.5,
      "scenario": "voip",
      "filename": "C_09_CHOP_FA.wav"
    },
    "voip_C_09_COMPSPKR_MK.wav": {
      "mos": 3.65318,
      "size": 21760,
      "bitrate": 24.365595912940023,
      "bitrate_target": 16,
      "time": 0.030701398849487305,
      "md5": "c8565cdcced2833ec8dcd129e0134327",
      "thresh": 2.5,
      "scenario": "voip",
      "filename": "C_09_COMPSPKR_MK.wav"
    },
    "voip_C_10_CHOP_FA.wav": {
      "mos": 3.18634,
      "size": 21799,
      "bitrate": 19.765052559997734,
      "bitrate_target": 16,
      "time": 0.026777982711791992,
      "md5": "97f5de636f7f05fa5a921455c5fbaecc",
      "thresh": 2.5,
      "scenario": "voip",
      "filename": "C_10_CHOP_FA.wav"
    },
    "voip_C_10_COMPSPKR_MK.wav": {
      "mos": 3.24952,
      "size": 20468,
      "bitrate": 22.49983957541831,
      "bitrate_target": 16,
      "time": 0.02880239486694336,
      "md5": "b2002dd46c69c2864401a9e4d62cf232",
      "thresh": 2.5,
      "scenario": "voip",
      "filename": "C_10_COMPSPKR_MK.wav"
    },
    "voip_C_11_CHOP_FA.wav": {
      "mos": 3.6195,
      "size": 19196,
      "bitrate": 18.885131844704322,
      "bitrate_target": 16,
      "time": 0.01157999038696289,
      "md5": "cd41333baa02d9f784bd83d1df17b072",
      "thresh": 2.5,
      "scenario": "voip",
      "filename": "C_11_CHOP_FA.wav"
    },
    "voip_C_11_COMPSPKR_MK.wav": {
      "mos": 3.84966,
      "size": 22101,
      "bitrate": 20.388376383763838,
      "bitrate_target": 16,
      "time": 0.013321161270141602,
      "md5": "b3e6f49f001be9a5f5b14612c35551b8",
      "thresh": 2.5,
      "scenario": "voip",
      "filename": "C_11_COMPSPKR_MK.wav"
    },
    "voip_C_12_CHOP_FA.wav": {
      "mos": 4.00919,
      "size": 22124,
      "bitrate": 19.521399674827165,
      "bitrate_target": 16,
      "time": 0.01738262176513672,
      "md5": "c3c6fb37448edf686592822b0e63203a",
      "thresh": 2.5,
      "scenario": "voip",
      "filename": "C_12_CHOP_FA.wav"
    },
    "voip_C_12_COMPSPKR_MK.wav": {
      "mos": 3.81627,
      "size": 20198,
      "bitrate": 19.76320939334638,
      "bitrate_target": 16,
      "time": 0.016831636428833008,
      "md5": "9cbe6e62136a44110c8cb36fba83a1e6",
      "thresh": 2.5,
      "scenario": "voip",
      "filename": "C_12_COMPSPKR_MK.wav"
    },
    "voip_C_13_CHOP_FA.wav": {
      "mos": 3.18028,
      "size": 22483,
      "bitrate": 19.936984744987736,
      "bitrate_target": 16,
      "time": 0.033379554748535156,
      "md5": "566ebe7eb11304bbf6a2c37273963f0a",
      "thresh": 2.5,
      "scenario": "voip",
      "filename": "C_13_CHOP_FA.wav"
    },
    "voip_C_13_COMPSPKR_MK.wav": {
      "mos": 3.32627,
      "size": 21196,
      "bitrate": 20.14828897338403,
      "bitrate_target": 16,
      "time": 0.046930789947509766,
      "md5": "129253bc1794c4093f4c23051ab43c1f",
      "thresh": 2.5,
      "scenario": "voip",
      "filename": "C_13_COMPSPKR_MK.wav"
    },
    "voip_C_14_CHOP_FA.wav": {
      "mos": 4.38759,
      "size": 19457,
      "bitrate": 20.059892548072618,
      "bitrate_target": 16,
      "time": 0.038378238677978516,
      "md5": "73443f94bc68327a752062e12d520b32",
      "thresh": 2.5,
      "scenario": "voip",
      "filename": "C_14_CHOP_FA.wav"
    },
    "voip_C_14_COMPSPKR_MK.wav": {
      "mos": 3.62861,
      "size": 21526,
      "bitrate": 20.980506822612085,
      "bitrate_target": 16,
      "time": 0.027088642120361328,
      "md5": "603037acc9691dc7194b8f4bc55fd257",
      "thresh": 2.5,
      "scenario": "voip",
      "filename": "C_14_COMPSPKR_MK.wav"
    },
    "voip_C_15_CHOP_FA.wav": {
      "mos": 3.47741,
      "size": 19503,
      "bitrate": 19.54575634199812,
      "bitrate_target": 16,
      "time": 0.018473148345947266,
      "md5": "3b903cb71af24399544ffeca51509e7c",
      "thresh": 2.5,
      "scenario": "voip",
      "filename": "C_15_CHOP_FA.wav"
    },
    "voip_C_16_NOISE_FA.wav": {
      "mos": 3.44946,
      "size": 18030,
      "bitrate": 16.628645816761182,
      "bitrate_target": 16,
      "time": 0.024480342864990234,
      "md5": "c625e618bb66f3b09ee712d958c8aa5b",
      "thresh": 2.5,
      "scenario": "voip",
      "filename": "C_16_NOISE_FA.wav"
    },
    "voip_C_15_NOISE_MK.wav": {
      "mos": 1.51937,
      "size": 17011,
      "bitrate": 15.928368690563277,
      "bitrate_target": 16,
      "time": 0.028946399688720703,
      "md5": "1c3efce12fbd8b514649877a1307152f",
      "thresh": 2.5,
      "scenario": "voip",
      "filename": "C_15_NOISE_MK.wav"
    },
    "voip_C_17_ECHO_MK.wav": {
      "mos": 4.07521,
      "size": 21257,
      "bitrate": 19.92775637551451,
      "bitrate_target": 16,
      "time": 0.0241546630859375,
      "md5": "6f5d5c81054ca7579d0d2f6ef3b408ed",
      "thresh": 2.5,
      "scenario": "voip",
      "filename": "C_17_ECHO_MK.wav"
    },
    "voip_C_18_ECHO_FA.wav": {
      "mos": 3.38806,
      "size": 25212,
      "bitrate": 20.1696,
      "bitrate_target": 16,
      "time": 0.041243553161621094,
      "md5": "7d5a39577d6673b3582b16c0dac13b3b",
      "thresh": 2.5,
      "scenario": "voip",
      "filename": "C_18_ECHO_FA.wav"
    },
    "voip_C_19_CHOP_MK.wav": {
      "mos": 3.53943,
      "size": 18703,
      "bitrate": 21.270213768320936,
      "bitrate_target": 16,
      "time": 0.03198885917663574,
      "md5": "70e21b485d79539dd652bba97b9252bb",
      "thresh": 2.5,
      "scenario": "voip",
      "filename": "C_19_CHOP_MK.wav"
    },
    "voip_C_20_CHOP_FA.wav": {
      "mos": 2.43292,
      "size": 22338,
      "bitrate": 19.505709958659082,
      "bitrate_target": 16,
      "time": 0.04130220413208008,
      "md5": "cd329bc4f57b8decfb23427bfe04230c",
      "thresh": 2.5,
      "scenario": "voip",
      "filename": "C_20_CHOP_FA.wav"
    },
    "voip_C_20_NOISE_MK.wav": {
      "mos": 3.19124,
      "size": 16706,
      "bitrate": 16.52538170926318,
      "bitrate_target": 16,
      "time": 0.03284192085266113,
      "md5": "8fb704c3bedb14499b6c54f0e0b71050",
      "thresh": 2.5,
      "scenario": "voip",
      "filename": "C_20_NOISE_MK.wav"
    },
    "voip_C_23_ECHO_FA.wav": {
      "mos": 2.93202,
      "size": 21933,
      "bitrate": 20.575046904315197,
      "bitrate_target": 16,
      "time": 0.02834773063659668,
      "md5": "6012e6733d5db710736510ffa6f68a9e",
      "thresh": 2.5,
      "scenario": "voip",
      "filename": "C_23_ECHO_FA.wav"
    },
    "voip_C_24_CHOP_MK.wav": {
      "mos": 4.40609,
      "size": 21257,
      "bitrate": 20.79941291585127,
      "bitrate_target": 16,
      "time": 0.01807379722595215,
      "md5": "26165d5f82b8c6b54ac617006a421b8a",
      "thresh": 2.5,
      "scenario": "voip",
      "filename": "C_24_CHOP_MK.wav"
    },
    "voip_C_22_ECHO_MK.wav": {
      "mos": 3.66033,
      "size": 21235,
      "bitrate": 19.55340699815838,
      "bitrate_target": 16,
      "time": 0.027681350708007812,
      "md5": "59e2144c312066afbe1bb922ba5f05c1",
      "thresh": 2.5,
      "scenario": "voip",
      "filename": "C_22_ECHO_MK.wav"
    },
    "voip_C_21_NOISE_FA.wav": {
      "mos": 3.13891,
      "size": 23417,
      "bitrate": 20.08319039451115,
      "bitrate_target": 16,
      "time": 0.030316591262817383,
      "md5": "3c75238f2797ccc59732065961efe43b",
      "thresh": 2.5,
      "scenario": "voip",
      "filename": "C_21_NOISE_FA.wav"
    },
    "vss_C_02_COMPSPKR_MK.wav": {
      "mos": 4.41249,
      "size": 42240,
      "bitrate": 44.127481305693934,
      "bitrate_target": 40,
      "time": 0.03401994705200195,
      "md5": "a0e2ecbbd17d9d6e1c21e8579e189ea4",
      "thresh": 3.0,
      "scenario": "vss",
      "filename": "C_02_COMPSPKR_MK.wav"
    },
    "vss_C_01_CHOP_FA.wav": {
      "mos": 4.10265,
      "size": 37480,
      "bitrate": 34.670345534441225,
      "bitrate_target": 40,
      "time": 0.044698476791381836,
      "md5": "dfeae7221d35396d9a879742618e6fb6",
      "thresh": 3.0,
      "scenario": "vss",
      "filename": "C_01_CHOP_FA.wav"
    },
    "vss_C_02_CHOP_FA.wav": {
      "mos": 4.02919,
      "size": 36042,
      "bitrate": 34.19848776871757,
      "bitrate_target": 40,
      "time": 0.05227851867675781,
      "md5": "8fbc2ac085d4a8dd2a671ec61a3ce2b8",
      "thresh": 3.0,
      "scenario": "vss",
      "filename": "C_02_CHOP_FA.wav"
    },
    "vss_C_01_COMPSPKR_MK.wav": {
      "mos": 4.19294,
      "size": 35947,
      "bitrate": 38.50937532473237,
      "bitrate_target": 40,
      "time": 0.04002070426940918,
      "md5": "284849e805d97d1f542cab2c9a79433f",
      "thresh": 3.0,
      "scenario": "vss",
      "filename": "C_01_COMPSPKR_MK.wav"
    },
    "vss_C_04_CHOP_FA.wav": {
      "mos": 3.79005,
      "size": 40548,
      "bitrate": 34.818924611055905,
      "bitrate_target": 40,
      "time": 0.028330087661743164,
      "md5": "3c4d70f3e796b5a73f252c21aaa8c740",
      "thresh": 3.0,
      "scenario": "vss",
      "filename": "C_04_CHOP_FA.wav"
    },
    "vss_C_03_CHOP_FA.wav": {
      "mos": 3.78267,
      "size": 38508,
      "bitrate": 34.594738335067575,
      "bitrate_target": 40,
      "time": 0.025800228118896484,
      "md5": "bd099c898c2afd3a7af31163b4621f1d",
      "thresh": 3.0,
      "scenario": "vss",
      "filename": "C_03_CHOP_FA.wav"
    },
    "vss_C_04_COMPSPKR_MK.wav": {
      "mos": 4.42117,
      "size": 45268,
      "bitrate": 51.65046029074207,
      "bitrate_target": 40,
      "time": 0.017447948455810547,
      "md5": "47a063600017311a4a473caa2f597fdc",
      "thresh": 3.0,
      "scenario": "vss",
      "filename": "C_04_COMPSPKR_MK.wav"
    },
    "vss_C_03_COMPSPKR_MK.wav": {
      "mos": 3.97347,
      "size": 48613,
      "bitrate": 51.038522861387804,
      "bitrate_target": 40,
      "time": 0.03636312484741211,
      "md5": "9870b17ca24f7c4ead929cf91e30ceba",
      "thresh": 3.0,
      "scenario": "vss",
      "filename": "C_03_COMPSPKR_MK.wav"
    },
    "vss_C_05_CHOP_FA.wav": {
      "mos": 3.78834,
      "size": 45254,
      "bitrate": 36.2032,
      "bitrate_target": 40,
      "time": 0.020535707473754883,
      "md5": "0b17143d86fa5c05df9e29a6f01cf965",
      "thresh": 3.0,
      "scenario": "vss",
      "filename": "C_05_CHOP_FA.wav"
    },
    "vss_C_05_COMPSPKR_MK.wav": {
      "mos": 3.96237,
      "size": 42647,
      "bitrate": 49.60169739295086,
      "bitrate_target": 40,
      "time": 0.016376972198486328,
      "md5": "391de2bc6da6986169b12bf6f4654c54",
      "thresh": 3.0,
      "scenario": "vss",
      "filename": "C_05_COMPSPKR_MK.wav"
    },
    "vss_C_06_CHOP_FA.wav": {
      "mos": 3.9769,
      "size": 39109,
      "bitrate": 34.70883899914224,
      "bitrate_target": 40,
      "time": 0.018365859985351562,
      "md5": "b307419c273d0d982e0c977fbed3ba4b",
      "thresh": 3.0,
      "scenario": "vss",
      "filename": "C_06_CHOP_FA.wav"
    },
    "vss_C_07_CHOP_FA.wav": {
      "mos": 3.92269,
      "size": 39423,
      "bitrate": 34.44984229713677,
      "bitrate_target": 40,
      "time": 0.019188642501831055,
      "md5": "624069716b6dc35cd7eccbe5abba3a6a",
      "thresh": 3.0,
      "scenario": "vss",
      "filename": "C_07_CHOP_FA.wav"
    },
    "vss_C_08_CHOP_FA.wav": {
      "mos": 4.25805,
      "size": 39422,
      "bitrate": 35.95334282661977,
      "bitrate_target": 40,
      "time": 0.01871514320373535,
      "md5": "516094d2a6e92aa16359a3d85dc58a31",
      "thresh": 3.0,
      "scenario": "vss",
      "filename": "C_08_CHOP_FA.wav"
    },
    "vss_C_07_COMPSPKR_MK.wav": {
      "mos": 3.94163,
      "size": 48261,
      "bitrate": 51.70114230803429,
      "bitrate_target": 40,
      "time": 0.019138813018798828,
      "md5": "7cd3ca90bf4b24f443caafcb2af94c42",
      "thresh": 3.0,
      "scenario": "vss",
      "filename": "C_07_COMPSPKR_MK.wav"
    },
    "vss_C_06_COMPSPKR_MK.wav": {
      "mos": 4.14833,
      "size": 42879,
      "bitrate": 46.89071777524163,
      "bitrate_target": 40,
      "time": 0.031383514404296875,
      "md5": "ebfaa5023b5b705f025ab68d779c031c",
      "thresh": 3.0,
      "scenario": "vss",
      "filename": "C_06_COMPSPKR_MK.wav"
    },
    "vss_C_08_COMPSPKR_MK.wav": {
      "mos": 4.63788,
      "size": 38220,
      "bitrate": 42.68304599706847,
      "bitrate_target": 40,
      "time": 0.01565694808959961,
      "md5": "7cf5a1daa0ee0f4d543c3aaa9740ac5e",
      "thresh": 3.0,
      "scenario": "vss",
      "filename": "C_08_COMPSPKR_MK.wav"
    },
    "vss_C_09_CHOP_FA.wav": {
      "mos": 3.9958,
      "size": 34146,
      "bitrate": 34.74231713124061,
      "bitrate_target": 40,
      "time": 0.015954971313476562,
      "md5": "8c36a387884ced0560a84f92c1078bf5",
      "thresh": 3.0,
      "scenario": "vss",
      "filename": "C_09_CHOP_FA.wav"
    },
    "vss_C_09_COMPSPKR_MK.wav": {
      "mos": 4.30188,
      "size": 45433,
      "bitrate": 50.87325915039541,
      "bitrate_target": 40,
      "time": 0.015273571014404297,
      "md5": "40856cb169930f77240e03d0284ba78d",
      "thresh": 3.0,
      "scenario": "vss",
      "filename": "C_09_COMPSPKR_MK.wav"
    },
    "vss_C_10_COMPSPKR_MK.wav": {
      "mos": 4.44836,
      "size": 43258,
      "bitrate": 47.55218195981264,
      "bitrate_target": 40,
      "time": 0.014208793640136719,
      "md5": "f0cc84200f5a564d98cccc48665df777",
      "thresh": 3.0,
      "scenario": "vss",
      "filename": "C_10_COMPSPKR_MK.wav"
    },
    "vss_C_11_CHOP_FA.wav": {
      "mos": 4.3308,
      "size": 33258,
      "bitrate": 32.7194058601363,
      "bitrate_target": 40,
      "time": 0.014369726181030273,
      "md5": "fbb348d476d87084e5c23daf0873a4f3",
      "thresh": 3.0,
      "scenario": "vss",
      "filename": "C_11_CHOP_FA.wav"
    },
    "vss_C_11_COMPSPKR_MK.wav": {
      "mos": 4.14376,
      "size": 37442,
      "bitrate": 34.54059040590406,
      "bitrate_target": 40,
      "time": 0.016475439071655273,
      "md5": "50d9d0e345bec1d0afdb4f051ac376fd",
      "thresh": 3.0,
      "scenario": "vss",
      "filename": "C_11_COMPSPKR_MK.wav"
    },
    "vss_C_10_CHOP_FA.wav": {
      "mos": 3.79385,
      "size": 37920,
      "bitrate": 34.38188875981073,
      "bitrate_target": 40,
      "time": 0.03153800964355469,
      "md5": "18f355ac2bf55ed0b057572a218c4b8b",
      "thresh": 3.0,
      "scenario": "vss",
      "filename": "C_10_CHOP_FA.wav"
    },
    "vss_C_12_COMPSPKR_MK.wav": {
      "mos": 4.25448,
      "size": 34118,
      "bitrate": 33.38356164383562,
      "bitrate_target": 40,
      "time": 0.016117572784423828,
      "md5": "0ec3148e577967c1276d16b9df718cb4",
      "thresh": 3.0,
      "scenario": "vss",
      "filename": "C_12_COMPSPKR_MK.wav"
    },
    "vss_C_12_CHOP_FA.wav": {
      "mos": 4.26671,
      "size": 39045,
      "bitrate": 34.4518645047743,
      "bitrate_target": 40,
      "time": 0.028888940811157227,
      "md5": "f8b57588a6a424efe6d439782098a98b",
      "thresh": 3.0,
      "scenario": "vss",
      "filename": "C_12_CHOP_FA.wav"
    },
    "vss_C_13_CHOP_FA.wav": {
      "mos": 3.95114,
      "size": 39430,
      "bitrate": 34.96487606168512,
      "bitrate_target": 40,
      "time": 0.02068161964416504,
      "md5": "ed7c9687f3e58ca10397cb5d11a5235b",
      "thresh": 3.0,
      "scenario": "vss",
      "filename": "C_13_CHOP_FA.wav"
    },
    "vss_C_14_CHOP_FA.wav": {
      "mos": 4.31288,
      "size": 33783,
      "bitrate": 34.82979647178585,
      "bitrate_target": 40,
      "time": 0.01780533790588379,
      "md5": "d08cc206bac5c8cbbc469d1e8cfcbca8",
      "thresh": 3.0,
      "scenario": "vss",
      "filename": "C_14_CHOP_FA.wav"
    },
    "vss_C_14_COMPSPKR_MK.wav": {
      "mos": 4.26648,
      "size": 36270,
      "bitrate": 35.35087719298246,
      "bitrate_target": 40,
      "time": 0.019042253494262695,
      "md5": "f85527cf9c2aa087d46903ff5498417f",
      "thresh": 3.0,
      "scenario": "vss",
      "filename": "C_14_COMPSPKR_MK.wav"
    },
    "vss_C_15_CHOP_FA.wav": {
      "mos": 4.32315,
      "size": 34965,
      "bitrate": 35.041653617287814,
      "bitrate_target": 40,
      "time": 0.017116785049438477,
      "md5": "187c39202a63be45faaf683d6013120a",
      "thresh": 3.0,
      "scenario": "vss",
      "filename": "C_15_CHOP_FA.wav"
    },
    "vss_C_13_COMPSPKR_MK.wav": {
      "mos": 3.91819,
      "size": 35500,
      "bitrate": 33.745247148288975,
      "bitrate_target": 40,
      "time": 0.03160548210144043,
      "md5": "18a6577f5f969c77ec1ac882744c0a68",
      "thresh": 3.0,
      "scenario": "vss",
      "filename": "C_13_COMPSPKR_MK.wav"
    },
    "vss_C_16_NOISE_FA.wav": {
      "mos": 4.30939,
      "size": 45553,
      "bitrate": 42.012462722735556,
      "bitrate_target": 40,
      "time": 0.018717527389526367,
      "md5": "3a8eb2049a1a2e83e4e4fa63b9477566",
      "thresh": 3.0,
      "scenario": "vss",
      "filename": "C_16_NOISE_FA.wav"
    },
    "vss_C_15_NOISE_MK.wav": {
      "mos": 4.24577,
      "size": 43749,
      "bitrate": 40.964681784930505,
      "bitrate_target": 40,
      "time": 0.020842552185058594,
      "md5": "df862a390a20783e421a03289811ab0a",
      "thresh": 3.0,
      "scenario": "vss",
      "filename": "C_15_NOISE_MK.wav"
    },
    "vss_C_17_ECHO_MK.wav": {
      "mos": 4.50436,
      "size": 37130,
      "bitrate": 34.80818526710513,
      "bitrate_target": 40,
      "time": 0.03548932075500488,
      "md5": "1605e0c32f75fb30a33f12185e4d5d05",
      "thresh": 3.0,
      "scenario": "vss",
      "filename": "C_17_ECHO_MK.wav"
    },
    "vss_C_19_CHOP_MK.wav": {
      "mos": 3.96703,
      "size": 30126,
      "bitrate": 34.26115917149316,
      "bitrate_target": 40,
      "time": 0.014821052551269531,
      "md5": "5ddc3457410e80b454930c609dd0f100",
      "thresh": 3.0,
      "scenario": "vss",
      "filename": "C_19_CHOP_MK.wav"
    },
    "vss_C_20_CHOP_FA.wav": {
      "mos": 4.0942,
      "size": 39752,
      "bitrate": 34.71174600575771,
      "bitrate_target": 40,
      "time": 0.018550395965576172,
      "md5": "1499a956ffd4998a8b88c8edead4348f",
      "thresh": 3.0,
      "scenario": "vss",
      "filename": "C_20_CHOP_FA.wav"
    },
    "vss_C_18_ECHO_FA.wav": {
      "mos": 4.21914,
      "size": 49081,
      "bitrate": 39.2648,
      "bitrate_target": 40,
      "time": 0.044764041900634766,
      "md5": "220d9387b2284b44ca2fc0a2f41d63bf",
      "thresh": 3.0,
      "scenario": "vss",
      "filename": "C_18_ECHO_FA.wav"
    },
    "vss_C_20_NOISE_MK.wav": {
      "mos": 4.23724,
      "size": 41340,
      "bitrate": 40.89304919555488,
      "bitrate_target": 40,
      "time": 0.030768871307373047,
      "md5": "b00b56655d51b39daacd34eb8b03dd07",
      "thresh": 3.0,
      "scenario": "vss",
      "filename": "C_20_NOISE_MK.wav"
    },
    "vss_C_21_NOISE_FA.wav": {
      "mos": 3.99851,
      "size": 40920,
      "bitrate": 35.094339622641506,
      "bitrate_target": 40,
      "time": 0.019273996353149414,
      "md5": "fbacd5c851f84865d065a170e7f28213",
      "thresh": 3.0,
      "scenario": "vss",
      "filename": "C_21_NOISE_FA.wav"
    },
    "vss_C_22_ECHO_MK.wav": {
      "mos": 4.21184,
      "size": 36620,
      "bitrate": 33.720073664825044,
      "bitrate_target": 40,
      "time": 0.017080068588256836,
      "md5": "c2fe3c053fbc3ab0382020bbdbf59743",
      "thresh": 3.0,
      "scenario": "vss",
      "filename": "C_22_ECHO_MK.wav"
    },
    "vss_C_24_CHOP_MK.wav": {
      "mos": 4.22822,
      "size": 35476,
      "bitrate": 34.71232876712329,
      "bitrate_target": 40,
      "time": 0.016579389572143555,
      "md5": "a7524ce3630dddba9f1eeca2496c937d",
      "thresh": 3.0,
      "scenario": "vss",
      "filename": "C_24_CHOP_MK.wav"
    },
    "vss_C_23_ECHO_FA.wav": {
      "mos": 4.05926,
      "size": 37162,
      "bitrate": 34.86116322701689,
      "bitrate_target": 40,
      "time": 0.0353541374206543,
      "md5": "1d1d26ec98eafddb9b0c46fc555b88fe",
      "thresh": 3.0,
      "scenario": "vss",
      "filename": "C_23_ECHO_FA.wav"
    },
    "music_low_12-German-male-speech.441.16b48k.wav": {
      "mos": 3.24751,
      "size": 67555,
      "bitrate": 68.93238977947605,
      "bitrate_target": 64,
      "time": 0.06703925132751465,
      "md5": "66f886a14e07bebba7a2f604a5bbd2e5",
      "thresh": 3.5,
      "scenario": "music_low",
      "filename": "12-German-male-speech.441.16b48k.wav"
    },
    "music_low_cst.wav": {
      "mos": 3.49949,
      "size": 53984,
      "bitrate": 66.23866668670776,
      "bitrate_target": 64,
      "time": 0.05437946319580078,
      "md5": "8d741b795c265077c50f9ee8db63ea65",
      "thresh": 3.5,
      "scenario": "music_low",
      "filename": "cst.wav"
    },
    "music_low_Shinsho_pool_3min45_4min4.16b48k.wav": {
      "mos": 4.28266,
      "size": 80122,
      "bitrate": 64.0976,
      "bitrate_target": 64,
      "time": 0.0747678279876709,
      "md5": "84cefd534e282533da1c33298d437a68",
      "thresh": 3.5,
      "scenario": "music_low",
      "filename": "Shinsho_pool_3min45_4min4.16b48k.wav"
    },
    "music_low_Coral.16b48k.wav": {
      "mos": 3.43335,
      "size": 80308,
      "bitrate": 64.2464,
      "bitrate_target": 64,
      "time": 0.16469669342041016,
      "md5": "af9d7537d6900a76c7e30de1fd842564",
      "thresh": 3.5,
      "scenario": "music_low",
      "filename": "Coral.16b48k.wav"
    },
    "music_std_12-German-male-speech.441.16b48k.wav": {
      "mos": 4.28052,
      "size": 135938,
      "bitrate": 138.70966178435964,
      "bitrate_target": 128,
      "time": 0.06011152267456055,
      "md5": "b65e04bbe0813689f51cf1e6e3866e3e",
      "thresh": 4.0,
      "scenario": "music_std",
      "filename": "12-German-male-speech.441.16b48k.wav"
    },
    "music_std_cst.wav": {
      "mos": 4.31559,
      "size": 108902,
      "bitrate": 133.62335654112047,
      "bitrate_target": 128,
      "time": 0.04774165153503418,
      "md5": "a8087bf40d2a3cd9a3184c70b4296daa",
      "thresh": 4.0,
      "scenario": "music_std",
      "filename": "cst.wav"
    },
    "music_std_Coral.16b48k.wav": {
      "mos": 4.5736,
      "size": 168352,
      "bitrate": 134.6816,
      "bitrate_target": 128,
      "time": 0.07513713836669922,
      "md5": "9594487347690d88d8cb03b6f07ac8ef",
      "thresh": 4.0,
      "scenario": "music_std",
      "filename": "Coral.16b48k.wav"
    },
    "music_std_Shinsho_pool_3min45_4min4.16b48k.wav": {
      "mos": 4.11221,
      "size": 158809,
      "bitrate": 127.0472,
      "bitrate_target": 128,
      "time": 0.11199021339416504,
      "md5": "62f937d96f128bf008d3d341432e735f",
      "thresh": 4.0,
      "scenario": "music_std",
      "filename": "Shinsho_pool_3min45_4min4.16b48k.wav"
    },
    "music_high_cst.wav": {
      "mos": 4.26616,
      "size": 213697,
      "bitrate": 262.20740135872455,
      "bitrate_target": 256,
      "time": 0.042185306549072266,
      "md5": "68f9a5d7f40a463a3334eadc9c3a5f4a",
      "thresh": 4.3,
      "scenario": "music_high",
      "filename": "cst.wav"
    },
    "music_high_Shinsho_pool_3min45_4min4.16b48k.wav": {
      "mos": 4.70448,
      "size": 317597,
      "bitrate": 254.0776,
      "bitrate_target": 256,
      "time": 0.06326055526733398,
      "md5": "2d039b583d2db138b2f56314d5d91ce0",
      "thresh": 4.3,
      "scenario": "music_high",
      "filename": "Shinsho_pool_3min45_4min4.16b48k.wav"
    },
    "music_high_Coral.16b48k.wav": {
      "mos": 4.64111,
      "size": 323204,
      "bitrate": 258.5632,
      "bitrate_target": 256,
      "time": 0.06493616104125977,
      "md5": "d32ea7a87c2baf8821e6a065d3d4c6b9",
      "thresh": 4.3,
      "scenario": "music_high",
      "filename": "Coral.16b48k.wav"
    },
    "music_high_12-German-male-speech.441.16b48k.wav": {
      "mos": 4.65026,
      "size": 265658,
      "bitrate": 271.0745437648738,
      "bitrate_target": 256,
      "time": 0.10501646995544434,
      "md5": "ed6e7a87b4b2edc75532fb3716f45db0",
      "thresh": 4.3,
      "scenario": "music_high",
      "filename": "12-German-male-speech.441.16b48k.wav"
    }
  },
  "throughput": {
    "noise.wav": 6.772425973331944,
    "silence.wav": 5.810875274337984,
    "sine.wav": 7.316625775335221,
    "sweep.wav": 4.733974564665307,
    "overall": 6.1584753969176145
  },
  "lib_size": 82968
}